{
  "slug": "business-process-automation", "serviceKey": "ai-automation", "enabled": true,
  "seo": { "title": "Business Process Automation | Fillip Technologies", "description": "Redesign and automate multi-team business processes for better speed, control, visibility, and scale.", "canonical": "/business-process-automation", "openGraph": { "title": "Business Process Automation", "description": "Build connected, measurable processes across teams and systems.", "image": "/images/tilt.png" }, "robots": { "index": true, "follow": true } },
  "content": { "hero": { "badge": "Business process automation", "title": "Build operations that are", "highlightedTitle": "connected and scalable.", "description": "Redesign complex business processes across departments, systems, approvals, and reporting with practical automation.", "primaryCta": "Discuss your process", "secondaryCta": "See the approach", "trustItems": ["End-to-end process mapping", "Controlled system integration", "Measurable operations"], "assistantName": "Fillip Process Assistant" }, "workflow": { "badge": "PROCESS TRANSFORMATION", "title": "From fragmented tasks to", "highlightedTitle": "connected operations.", "description": "We map the current process, remove unnecessary friction, automate repeatable steps, and improve visibility.", "steps": ["Map process", "Find bottlenecks", "Redesign flow", "Connect systems", "Automate tasks", "Measure outcomes", "Improve continuously"] }, "results": { "badge": "DESIGNED FOR OPERATIONAL IMPACT", "metrics": [{ "value": "Faster", "label": "Cycle times" }, { "value": "Lower", "label": "Manual effort" }, { "value": "Clear", "label": "Process visibility" }, { "value": "Better", "label": "Team consistency" }] }, "cta": { "title": "Ready to improve a business process?", "description": "Transform a manual, fragmented operation into a connected and measurable system.", "primaryCta": "Schedule consultation", "secondaryCta": "Contact us", "emailSubject": "Business Process Automation" } },
  "faq": { "badge": "PROCESS AUTOMATION FAQS", "title": "Frequently Asked Questions", "description": "Common questions about business process automation.", "items": [{ "question": "How is process automation different from task automation?", "answer": "Process automation coordinates multiple steps, people, rules, and systems across an end-to-end business outcome." }] }
}
